casibase_python_sdk/__init__.py
casibase_python_sdk/file.py
casibase_python_sdk/main.py
casibase_python_sdk/prompt.py
casibase_python_sdk/properties.py
casibase_python_sdk/record.py
casibase_python_sdk/store.py
casibase_python_sdk/task.py
casibase_python_sdk/usage_info.py
casibase_python_sdk-1.3.0.dist-info/METADATA
casibase_python_sdk-1.3.0.dist-info/WHEEL
casibase_python_sdk-1.3.0.dist-info/licenses/LICENSE
casibase_python_sdk-1.3.0.dist-info/RECORD
