Metadata-Version: 2.4
Name: casibase-python-sdk
Version: 1.3.0
Dynamic: Requires-Dist
Summary: Python SDK built for Casibase
Project-URL: Home, https://github.com/casibase/casibase-python-sdk
Author-email: Casibase <admin@casibase.org>
License:                                  Apache License
License-File: LICENSE
Keywords: Casibase
Classifier: Intended Audience :: Developers
Classifier: License :: OSI Approved :: Apache Software License
Classifier: Operating System :: OS Independent
Classifier: Programming Language :: Python
Classifier: Programming Language :: Python :: 3.6
Classifier: Programming Language :: Python :: 3.7
Classifier: Programming Language :: Python :: 3.8
Classifier: Programming Language :: Python :: 3.9
Classifier: Programming Language :: Python :: 3.10
Classifier: Programming Language :: Python :: 3.11
Classifier: Programming Language :: Python :: 3.12
Requires-Python: >=3.6
